{"symbol":"Pa","Z":91,"asd_version":"5.12","columns":["lam_air","lam_vac","Aki","Ek","gk","Ei","gi","int","acc","src"],"stages":{"1":[[350.496738,350.597,null,null,null,null,null,"3000","",0],[357.056051,357.158,null,null,null,null,null,"3000","",0],[357.182018,357.284,null,null,null,null,null,"3000","",0],[361.806825,361.91,null,null,null,null,null,"3000","",0],[363.652349,363.756,null,null,null,null,null,"10000","",0],[370.273636,370.379,null,null,null,null,null,"3000","",0],[375.267342,375.374,null,null,null,null,null,"3000","",0],[387.335206,387.445,null,null,null,null,null,"3000","",0],[393.182683,393.294,null,null,null,null,null,"3000","",0],[398.182378,398.295,null,null,null,null,null,"3000","",0],[398.223367,398.336,null,null,null,null,null,"10000","",0],[603.577861,603.745,null,null,null,null,null,"3000l","",0],[616.25646,616.427,null,null,null,null,null,"3000","",0],[635.861198,636.037,null,null,null,null,null,"3000l","",0],[637.924644,638.101,null,null,null,null,null,"3000","",0],[643.89704,644.075,null,null,null,null,null,"3000l","",0],[679.274527,679.462,null,null,null,null,null,"3000w","",0],[694.572409,694.764,null,null,null,null,null,"10000","",0],[696.009022,696.201,null,null,null,null,null,"3000","",0],[696.177977,696.37,null,null,null,null,null,"3000w","",0],[699.273143,699.466,null,null,null,null,null,"3000s","",0],[707.626893,707.822,null,null,null,null,null,"3000","",0],[710.094229,710.29,null,null,null,null,null,"3000w","",0],[711.488853,711.685,null,null,null,null,null,"10000s","",0],[717.155326,717.353,null,null,null,null,null,"3000w","",0],[722.712828,722.912,null,null,null,null,null,"3000","",0],[731.879357,732.081,null,null,null,null,null,"3000","",0],[736.825024,737.028,null,null,null,null,null,"10000l","",0],[747.189229,747.395,null,null,null,null,null,"3000w","",0],[749.314656,749.521,null,null,null,null,null,"10000w","",0],[755.825899,756.034,null,null,null,null,null,"3000w","",0],[760.819552,761.029,null,null,null,null,null,"10000w","",0],[762.67905,762.889,null,null,null,null,null,"10000","",0],[763.517824,763.728,null,null,null,null,null,"10000s","",0],[766.933902,767.145,null,null,null,null,null,"10000","",0],[767.919636,768.131,null,null,null,null,null,"3000","",0],[774.918746,775.132,null,null,null,null,null,"10000w","",0],[787.295405,787.512,null,null,null,null,null,"3000","",0],[794.556444,794.775,null,null,null,null,null,"3000l","",0],[803.933911,804.155,null,null,null,null,null,"10000","",0],[809.984277,810.207,null,null,null,null,null,"10000w","",0],[819.903596,820.129,null,null,null,null,null,"10000","",0],[827.186628,827.414,null,null,null,null,null,"10000","",0],[835.898273,836.128,null,null,null,null,null,"3000s","",0],[836.959986,837.19,null,null,null,null,null,"3000s","",0],[844.104055,844.336,null,null,null,null,null,"3000w","",0],[853.265577,853.5,null,null,null,null,null,"10000w","",0],[857.296487,857.532,null,null,null,null,null,"10000s","",0],[863.990677,864.228,null,null,null,null,null,"3000w","",0],[865.351309,865.589,null,null,null,null,null,"3000w","",0],[873.527097,873.767,null,null,null,null,null,"10000","",0],[1092.331811,1092.631,null,null,null,null,null,"3000","",0]],"2":[[259.91631,259.994,null,null,null,null,null,"3000","",0],[269.921917,270.002,null,null,null,null,null,"3000","",0],[282.278916,282.362,null,null,null,null,null,"3000","",0],[287.141722,287.226,null,null,null,null,null,"3000w","",0],[289.114236,289.199,null,null,null,null,null,"3000w","",0],[301.110261,301.198,null,null,null,null,null,"3000l","",0],[303.358699,303.447,null,null,null,null,null,"3000s","",0],[307.123757,307.213,null,null,null,null,null,"3000l","",0],[309.323206,309.413,null,null,null,null,null,"3000l","",0],[312.623377,312.714,null,null,null,null,null,"3000l","",0],[314.627872,314.719,null,null,null,null,null,"3000l","",0],[317.089251,317.181,null,null,null,null,null,"3000l","",0],[317.154235,317.246,null,null,null,null,null,"3000l","",0],[324.058488,324.152,null,null,null,null,null,"3000l","",0],[327.445629,327.54,null,null,null,null,null,"3000","",0],[333.269147,333.365,null,null,null,null,null,"3000l","",0],[334.665791,334.762,null,null,null,null,null,"3000s","",0],[345.282077,345.381,null,null,null,null,null,"3000l","",0],[353.065078,353.166,null,null,null,null,null,"3000s","",0],[395.26214,395.374,null,null,null,null,null,"3000s","",0],[395.785004,395.897,null,null,null,null,null,"10000l","",0],[397.006685,397.119,null,null,null,null,null,"3000s","",0],[401.295565,401.409,null,null,null,null,null,"3000l","",0],[401.821427,401.935,null,null,null,null,null,"3000s","",0],[403.016115,403.13,null,null,null,null,null,"3000","",0],[404.692677,404.807,null,null,null,null,null,"3000s","",0],[405.620434,405.735,null,null,null,null,null,"10000s","",0],[407.040062,407.155,null,null,null,null,null,"10000s","",0],[417.618291,417.736,null,null,null,null,null,"3000l","",0],[421.723213,421.842,null,null,null,null,null,"10000l","",0],[424.808403,424.928,null,null,null,null,null,"10000s","",0],[429.134266,429.255,null,null,null,null,null,"3000s","",0],[460.143089,460.272,null,null,null,null,null,"3000s","",0]]}}